vision/__init__.py
vision/vision.py
kais_kit_vision_4-0.0.1.dist-info/METADATA
kais_kit_vision_4-0.0.1.dist-info/WHEEL
kais_kit_vision_4-0.0.1.dist-info/top_level.txt
kais_kit_vision_4-0.0.1.dist-info/RECORD
